Metadata-Version: 1.1
Name: localstack-client
Version: 1.29
Summary: A lightweight Python client for LocalStack.
Home-page: https://github.com/localstack/localstack-python-client
Author: LocalStack Team
Author-email: info@localstack.cloud
License: Apache License 2.0
Platform: UNKNOWN
Classifier: Programming Language :: Python :: 2
Classifier: Programming Language :: Python :: 2.6
Classifier: Programming Language :: Python :: 2.7
Classifier: Programming Language :: Python :: 3
Classifier: Programming Language :: Python :: 3.3
Classifier: Programming Language :: Python :: 3.4
Classifier: Programming Language :: Python :: 3.6
Classifier: Programming Language :: Python :: 3.7
Classifier: Programming Language :: Python :: 3.8
Classifier: Programming Language :: Python :: 3.9
Classifier: License :: OSI Approved :: Apache Software License
Classifier: Topic :: Software Development :: Testing
